access_3dprompt/__init__.py
access_3dprompt-0.1.0.dist-info/METADATA
access_3dprompt-0.1.0.dist-info/WHEEL
access_3dprompt-0.1.0.dist-info/licenses/LICENSE
access_3dprompt-0.1.0.dist-info/RECORD
