Metadata-Version: 2.3
Name: access-3dprompt
Version: 0.1.0
Summary: The official Python library for the 3DPrompt API
License-File: LICENSE
Requires-Python: >=3.8
Requires-Dist: pytest>=8.1.1
